{
"skeleton": { "hash": "EYBfQxvWNeBQJpLwJ43uO0Ztk9s", "spine": "3.7.87", "width": 800, "height": 800, "images": "../output/1x/", "audio": "../../audio/output/" },
"bones": [
	{ "name": "root" },
	{ "name": "rocket", "parent": "root", "length": 300.89, "rotation": 90, "y": -291.32 }
],
"slots": [
	{ "name": "bg", "bone": "root" },
	{ "name": "rocket", "bone": "rocket", "attachment": "rocket" },
	{ "name": "thruster", "bone": "rocket", "attachment": "thruster" }
],
"skins": {
	"default": {
		"rocket": {
			"rocket": { "x": 133.55, "width": 341, "height": 224 }
		},
		"thruster": {
			"thruster": { "type": "point" }
		}
	}
},
"events": {
	"rocket": { "audio": "rocket.ogg" },
	"thruster": {}
},
"animations": {
	"animation": {
		"bones": {
			"rocket": {
				"translate": [
					{ "time": 0, "x": 0, "y": -423.17 },
					{ "time": 16, "x": 0, "y": 729.98 }
				]
			}
		},
		"events": [
			{ "time": 0, "name": "rocket", "string": "loop" },
			{ "time": 0, "name": "thruster", "string": "thruster;start" },
			{ "time": 17, "name": "thruster", "string": "thruster;stop" }
		]
	},
	"hide": {
		"slots": {
			"rocket": {
				"color": [
					{ "time": 0, "color": "ffffffff" },
					{ "time": 1, "color": "ffffff00" }
				]
			}
		}
	},
	"show": {
		"bones": {
			"rocket": {
				"translate": [
					{ "time": 0, "x": 0, "y": -423.17 }
				]
			}
		}
	}
}
}